[
    {
        "mot": "ضائقتكما"
    },
    {
        "mot": "ضائقتهما"
    },
    {
        "mot": "ضابطاكما"
    },
    {
        "mot": "ضابطاهما"
    },
    {
        "mot": "ضابطتاكم"
    },
    {
        "mot": "ضابطتاكن"
    },
    {
        "mot": "ضابطتانا"
    },
    {
        "mot": "ضابطتاها"
    },
    {
        "mot": "ضابطتاهم"
    },
    {
        "mot": "ضابطتاهن"
    },
    {
        "mot": "ضابطتكما"
    },
    {
        "mot": "ضابطتهما"
    },
    {
        "mot": "ضابطتيكم"
    },
    {
        "mot": "ضابطتيكن"
    },
    {
        "mot": "ضابطتينا"
    },
    {
        "mot": "ضابطتيها"
    },
    {
        "mot": "ضابطتيهم"
    },
    {
        "mot": "ضابطتيهن"
    },
    {
        "mot": "ضابطيكما"
    },
    {
        "mot": "ضابطيهما"
    },
    {
        "mot": "ضاجعاكما"
    },
    {
        "mot": "ضاجعاهما"
    },
    {
        "mot": "ضاجعتاكم"
    },
    {
        "mot": "ضاجعتاكن"
    },
    {
        "mot": "ضاجعتانا"
    },
    {
        "mot": "ضاجعتاني"
    },
    {
        "mot": "ضاجعتاها"
    },
    {
        "mot": "ضاجعتاهم"
    },
    {
        "mot": "ضاجعتاهن"
    },
    {
        "mot": "ضاجعتكما"
    },
    {
        "mot": "ضاجعتماه"
    },
    {
        "mot": "ضاجعتموه"
    },
    {
        "mot": "ضاجعتننا"
    },
    {
        "mot": "ضاجعتنني"
    },
    {
        "mot": "ضاجعتنها"
    },
    {
        "mot": "ضاجعتنهم"
    },
    {
        "mot": "ضاجعتنهن"
    },
    {
        "mot": "ضاجعتهما"
    },
    {
        "mot": "ضاجعناكم"
    },
    {
        "mot": "ضاجعناكن"
    },
    {
        "mot": "ضاجعناها"
    },
    {
        "mot": "ضاجعناهم"
    },
    {
        "mot": "ضاجعناهن"
    },
    {
        "mot": "ضاجعنكما"
    },
    {
        "mot": "ضاجعنهما"
    },
    {
        "mot": "ضاجعوكما"
    },
    {
        "mot": "ضاجعوهما"
    },
    {
        "mot": "ضاحكاتكم"
    },
    {
        "mot": "ضاحكاتكن"
    },
    {
        "mot": "ضاحكاتنا"
    },
    {
        "mot": "ضاحكاتها"
    },
    {
        "mot": "ضاحكاتهم"
    },
    {
        "mot": "ضاحكاتهن"
    },
    {
        "mot": "ضاحكاكما"
    },
    {
        "mot": "ضاحكاهما"
    },
    {
        "mot": "ضاحكتاكم"
    },
    {
        "mot": "ضاحكتاكن"
    },
    {
        "mot": "ضاحكتانا"
    },
    {
        "mot": "ضاحكتاها"
    },
    {
        "mot": "ضاحكتاهم"
    },
    {
        "mot": "ضاحكتاهن"
    },
    {
        "mot": "ضاحكتكما"
    },
    {
        "mot": "ضاحكتهما"
    },
    {
        "mot": "ضاحكتيكم"
    },
    {
        "mot": "ضاحكتيكن"
    },
    {
        "mot": "ضاحكتينا"
    },
    {
        "mot": "ضاحكتيها"
    },
    {
        "mot": "ضاحكتيهم"
    },
    {
        "mot": "ضاحكتيهن"
    },
    {
        "mot": "ضاحكوكما"
    },
    {
        "mot": "ضاحكوهما"
    },
    {
        "mot": "ضاحكيكما"
    },
    {
        "mot": "ضاحكيهما"
    },
    {
        "mot": "ضاحيتاكم"
    },
    {
        "mot": "ضاحيتاكن"
    },
    {
        "mot": "ضاحيتانا"
    },
    {
        "mot": "ضاحيتاها"
    },
    {
        "mot": "ضاحيتاهم"
    },
    {
        "mot": "ضاحيتاهن"
    },
    {
        "mot": "ضاحيتكما"
    },
    {
        "mot": "ضاحيتهما"
    },
    {
        "mot": "ضاحيتيكم"
    },
    {
        "mot": "ضاحيتيكن"
    },
    {
        "mot": "ضاحيتينا"
    },
    {
        "mot": "ضاحيتيها"
    },
    {
        "mot": "ضاحيتيهم"
    },
    {
        "mot": "ضاحيتيهن"
    },
    {
        "mot": "ضادتاكما"
    },
    {
        "mot": "ضادتاهما"
    },
    {
        "mot": "ضارباكما"
    },
    {
        "mot": "ضارباهما"
    },
    {
        "mot": "ضاربتاكم"
    },
    {
        "mot": "ضاربتاكن"
    },
    {
        "mot": "ضاربتانا"
    },
    {
        "mot": "ضاربتاني"
    },
    {
        "mot": "ضاربتاها"
    },
    {
        "mot": "ضاربتاهم"
    },
    {
        "mot": "ضاربتاهن"
    },
    {
        "mot": "ضاربتكما"
    },
    {
        "mot": "ضاربتماه"
    },
    {
        "mot": "ضاربتموه"
    },
    {
        "mot": "ضاربتننا"
    },
    {
        "mot": "ضاربتنني"
    },
    {
        "mot": "ضاربتنها"
    },
    {
        "mot": "ضاربتنهم"
    },
    {
        "mot": "ضاربتنهن"
    },
    {
        "mot": "ضاربتهما"
    },
    {
        "mot": "ضاربناكم"
    },
    {
        "mot": "ضاربناكن"
    },
    {
        "mot": "ضاربناها"
    },
    {
        "mot": "ضاربناهم"
    },
    {
        "mot": "ضاربناهن"
    },
    {
        "mot": "ضاربنكما"
    },
    {
        "mot": "ضاربنهما"
    },
    {
        "mot": "ضاربوكما"
    },
    {
        "mot": "ضاربوهما"
    },
    {
        "mot": "ضاربيهما"
    },
    {
        "mot": "ضارتاكما"
    },
    {
        "mot": "ضارتاهما"
    },
    {
        "mot": "ضارعاتكم"
    },
    {
        "mot": "ضارعاتكن"
    },
    {
        "mot": "ضارعاتنا"
    },
    {
        "mot": "ضارعاتها"
    },
    {
        "mot": "ضارعاتهم"
    },
    {
        "mot": "ضارعاتهن"
    },
    {
        "mot": "ضارعاكما"
    },
    {
        "mot": "ضارعاهما"
    },
    {
        "mot": "ضارعتاكم"
    },
    {
        "mot": "ضارعتاكن"
    },
    {
        "mot": "ضارعتانا"
    },
    {
        "mot": "ضارعتاني"
    },
    {
        "mot": "ضارعتاها"
    },
    {
        "mot": "ضارعتاهم"
    },
    {
        "mot": "ضارعتاهن"
    },
    {
        "mot": "ضارعتكما"
    },
    {
        "mot": "ضارعتماه"
    },
    {
        "mot": "ضارعتموه"
    },
    {
        "mot": "ضارعتننا"
    },
    {
        "mot": "ضارعتنني"
    },
    {
        "mot": "ضارعتنها"
    },
    {
        "mot": "ضارعتنهم"
    },
    {
        "mot": "ضارعتنهن"
    },
    {
        "mot": "ضارعتهما"
    },
    {
        "mot": "ضارعتيكم"
    },
    {
        "mot": "ضارعتيكن"
    },
    {
        "mot": "ضارعتينا"
    },
    {
        "mot": "ضارعتيها"
    },
    {
        "mot": "ضارعتيهم"
    },
    {
        "mot": "ضارعتيهن"
    },
    {
        "mot": "ضارعناكم"
    },
    {
        "mot": "ضارعناكن"
    },
    {
        "mot": "ضارعناها"
    },
    {
        "mot": "ضارعناهم"
    },
    {
        "mot": "ضارعناهن"
    },
    {
        "mot": "ضارعنكما"
    },
    {
        "mot": "ضارعنهما"
    },
    {
        "mot": "ضارعوكما"
    },
    {
        "mot": "ضارعوهما"
    },
    {
        "mot": "ضارعيهما"
    },
    {
        "mot": "ضاعتاكما"
    },
    {
        "mot": "ضاعتاهما"
    },
    {
        "mot": "ضاعفاكما"
    },
    {
        "mot": "ضاعفاهما"
    },
    {
        "mot": "ضاعفتاكم"
    },
    {
        "mot": "ضاعفتاكن"
    },
    {
        "mot": "ضاعفتانا"
    },
    {
        "mot": "ضاعفتاني"
    },
    {
        "mot": "ضاعفتاها"
    },
    {
        "mot": "ضاعفتاهم"
    },
    {
        "mot": "ضاعفتاهن"
    },
    {
        "mot": "ضاعفتكما"
    },
    {
        "mot": "ضاعفتماه"
    },
    {
        "mot": "ضاعفتموه"
    },
    {
        "mot": "ضاعفتننا"
    },
    {
        "mot": "ضاعفتنني"
    },
    {
        "mot": "ضاعفتنها"
    },
    {
        "mot": "ضاعفتنهم"
    },
    {
        "mot": "ضاعفتنهن"
    },
    {
        "mot": "ضاعفتهما"
    },
    {
        "mot": "ضاعفناكم"
    },
    {
        "mot": "ضاعفناكن"
    },
    {
        "mot": "ضاعفناها"
    },
    {
        "mot": "ضاعفناهم"
    },
    {
        "mot": "ضاعفناهن"
    },
    {
        "mot": "ضاعفنكما"
    },
    {
        "mot": "ضاعفنهما"
    },
    {
        "mot": "ضاعفوكما"
    },
    {
        "mot": "ضاعفوهما"
    },
    {
        "mot": "ضاغطاكما"
    },
    {
        "mot": "ضاغطاهما"
    },
    {
        "mot": "ضاغطتاكم"
    },
    {
        "mot": "ضاغطتاكن"
    },
    {
        "mot": "ضاغطتانا"
    },
    {
        "mot": "ضاغطتاها"
    },
    {
        "mot": "ضاغطتاهم"
    },
    {
        "mot": "ضاغطتاهن"
    },
    {
        "mot": "ضاغطتكما"
    },
    {
        "mot": "ضاغطتهما"
    },
    {
        "mot": "ضاغطتيكم"
    },
    {
        "mot": "ضاغطتيكن"
    },
    {
        "mot": "ضاغطتينا"
    },
    {
        "mot": "ضاغطتيها"
    },
    {
        "mot": "ضاغطتيهم"
    },
    {
        "mot": "ضاغطتيهن"
    },
    {
        "mot": "ضاغطيكما"
    },
    {
        "mot": "ضاغطيهما"
    },
    {
        "mot": "ضافراكما"
    },
    {
        "mot": "ضافراهما"
    },
    {
        "mot": "ضافرتاكم"
    },
    {
        "mot": "ضافرتاكن"
    },
    {
        "mot": "ضافرتانا"
    },
    {
        "mot": "ضافرتاني"
    },
    {
        "mot": "ضافرتاها"
    },
    {
        "mot": "ضافرتاهم"
    },
    {
        "mot": "ضافرتاهن"
    },
    {
        "mot": "ضافرتكما"
    },
    {
        "mot": "ضافرتماه"
    },
    {
        "mot": "ضافرتموه"
    },
    {
        "mot": "ضافرتننا"
    },
    {
        "mot": "ضافرتنني"
    },
    {
        "mot": "ضافرتنها"
    },
    {
        "mot": "ضافرتنهم"
    },
    {
        "mot": "ضافرتنهن"
    },
    {
        "mot": "ضافرتهما"
    },
    {
        "mot": "ضافرناكم"
    },
    {
        "mot": "ضافرناكن"
    },
    {
        "mot": "ضافرناها"
    },
    {
        "mot": "ضافرناهم"
    },
    {
        "mot": "ضافرناهن"
    },
    {
        "mot": "ضافرنكما"
    },
    {
        "mot": "ضافرنهما"
    },
    {
        "mot": "ضافروكما"
    },
    {
        "mot": "ضافروهما"
    },
    {
        "mot": "ضافريهما"
    },
    {
        "mot": "ضافيتاكم"
    },
    {
        "mot": "ضافيتاكن"
    },
    {
        "mot": "ضافيتانا"
    },
    {
        "mot": "ضافيتاها"
    },
    {
        "mot": "ضافيتاهم"
    },
    {
        "mot": "ضافيتاهن"
    },
    {
        "mot": "ضافيتكما"
    },
    {
        "mot": "ضافيتهما"
    },
    {
        "mot": "ضافيتيكم"
    },
    {
        "mot": "ضافيتيكن"
    },
    {
        "mot": "ضافيتينا"
    },
    {
        "mot": "ضافيتيها"
    },
    {
        "mot": "ضافيتيهم"
    },
    {
        "mot": "ضافيتيهن"
    },
    {
        "mot": "ضامراكما"
    },
    {
        "mot": "ضامراهما"
    },
    {
        "mot": "ضامرتاكم"
    },
    {
        "mot": "ضامرتاكن"
    },
    {
        "mot": "ضامرتانا"
    },
    {
        "mot": "ضامرتاها"
    },
    {
        "mot": "ضامرتاهم"
    },
    {
        "mot": "ضامرتاهن"
    },
    {
        "mot": "ضامرتكما"
    },
    {
        "mot": "ضامرتهما"
    },
    {
        "mot": "ضامرتيكم"
    },
    {
        "mot": "ضامرتيكن"
    },
    {
        "mot": "ضامرتينا"
    },
    {
        "mot": "ضامرتيها"
    },
    {
        "mot": "ضامرتيهم"
    },
    {
        "mot": "ضامرتيهن"
    },
    {
        "mot": "ضامروكما"
    },
    {
        "mot": "ضامروهما"
    },
    {
        "mot": "ضامريكما"
    },
    {
        "mot": "ضامريهما"
    },
    {
        "mot": "ضامناتكم"
    },
    {
        "mot": "ضامناتكن"
    },
    {
        "mot": "ضامناتنا"
    },
    {
        "mot": "ضامناتها"
    },
    {
        "mot": "ضامناتهم"
    },
    {
        "mot": "ضامناتهن"
    },
    {
        "mot": "ضامناكما"
    },
    {
        "mot": "ضامناهما"
    },
    {
        "mot": "ضامنتاكم"
    },
    {
        "mot": "ضامنتاكن"
    },
    {
        "mot": "ضامنتانا"
    },
    {
        "mot": "ضامنتاها"
    },
    {
        "mot": "ضامنتاهم"
    },
    {
        "mot": "ضامنتاهن"
    },
    {
        "mot": "ضامنتكما"
    },
    {
        "mot": "ضامنتهما"
    },
    {
        "mot": "ضامنتيكم"
    },
    {
        "mot": "ضامنتيكن"
    },
    {
        "mot": "ضامنتينا"
    },
    {
        "mot": "ضامنتيها"
    },
    {
        "mot": "ضامنتيهم"
    },
    {
        "mot": "ضامنتيهن"
    },
    {
        "mot": "ضامنوكما"
    },
    {
        "mot": "ضامنوهما"
    },
    {
        "mot": "ضامنيكما"
    },
    {
        "mot": "ضامنيهما"
    },
    {
        "mot": "ضاويتاكم"
    },
    {
        "mot": "ضاويتاكن"
    },
    {
        "mot": "ضاويتانا"
    },
    {
        "mot": "ضاويتاها"
    },
    {
        "mot": "ضاويتاهم"
    },
    {
        "mot": "ضاويتاهن"
    },
    {
        "mot": "ضاويتكما"
    },
    {
        "mot": "ضاويتهما"
    },
    {
        "mot": "ضاويتيكم"
    },
    {
        "mot": "ضاويتيكن"
    },
    {
        "mot": "ضاويتينا"
    },
    {
        "mot": "ضاويتيها"
    },
    {
        "mot": "ضاويتيهم"
    },
    {
        "mot": "ضاويتيهن"
    },
    {
        "mot": "ضايقاكما"
    },
    {
        "mot": "ضايقاهما"
    },
    {
        "mot": "ضايقتاكم"
    },
    {
        "mot": "ضايقتاكن"
    },
    {
        "mot": "ضايقتانا"
    },
    {
        "mot": "ضايقتاني"
    },
    {
        "mot": "ضايقتاها"
    },
    {
        "mot": "ضايقتاهم"
    },
    {
        "mot": "ضايقتاهن"
    },
    {
        "mot": "ضايقتكما"
    },
    {
        "mot": "ضايقتماه"
    },
    {
        "mot": "ضايقتموه"
    },
    {
        "mot": "ضايقتننا"
    },
    {
        "mot": "ضايقتنني"
    },
    {
        "mot": "ضايقتنها"
    },
    {
        "mot": "ضايقتنهم"
    },
    {
        "mot": "ضايقتنهن"
    },
    {
        "mot": "ضايقتهما"
    },
    {
        "mot": "ضايقناكم"
    },
    {
        "mot": "ضايقناكن"
    },
    {
        "mot": "ضايقناها"
    },
    {
        "mot": "ضايقناهم"
    },
    {
        "mot": "ضايقناهن"
    },
    {
        "mot": "ضايقنكما"
    },
    {
        "mot": "ضايقنهما"
    },
    {
        "mot": "ضايقوكما"
    },
    {
        "mot": "ضايقوهما"
    },
    {
        "mot": "ضبابيتان"
    },
    {
        "mot": "ضبابيتاي"
    },
    {
        "mot": "ضبابيتنا"
    },
    {
        "mot": "ضبابيتين"
    },
    {
        "mot": "ضبابيكما"
    },
    {
        "mot": "ضبابيهما"
    },
    {
        "mot": "ضبطتاكما"
    },
    {
        "mot": "ضبطتاهما"
    },
    {
        "mot": "ضبطتمانا"
    },
    {
        "mot": "ضبطتماني"
    },
    {
        "mot": "ضبطتماها"
    },
    {
        "mot": "ضبطتماهم"
    },
    {
        "mot": "ضبطتماهن"
    },
    {
        "mot": "ضبطتمونا"
    },
    {
        "mot": "ضبطتموني"
    },
    {
        "mot": "ضبطتموها"
    },
    {
        "mot": "ضبطتموهم"
    },
    {
        "mot": "ضبطتموهن"
    },
    {
        "mot": "ضبطتنهما"
    },
    {
        "mot": "ضبطناكما"
    },
    {
        "mot": "ضبطناهما"
    },
    {
        "mot": "ضجرتاكما"
    },
    {
        "mot": "ضجرتاهما"
    },
    {
        "mot": "ضحالتكما"
    },
    {
        "mot": "ضحالتهما"
    },
    {
        "mot": "ضحاياكما"
    },
    {
        "mot": "ضحاياهما"
    },
    {
        "mot": "ضحكاتهما"
    },
    {
        "mot": "ضحيتاكما"
    },
    {
        "mot": "ضحيتاهما"
    },
    {
        "mot": "ضحيتيكما"
    },
    {
        "mot": "ضحيتيهما"
    },
    {
        "mot": "ضخامتكما"
    },
    {
        "mot": "ضخامتهما"
    },
    {
        "mot": "ضخمتاكما"
    },
    {
        "mot": "ضخمتاهما"
    },
    {
        "mot": "ضخمتمانا"
    },
    {
        "mot": "ضخمتماني"
    },
    {
        "mot": "ضخمتماها"
    },
    {
        "mot": "ضخمتماهم"
    },
    {
        "mot": "ضخمتماهن"
    },
    {
        "mot": "ضخمتمونا"
    },
    {
        "mot": "ضخمتموني"
    },
    {
        "mot": "ضخمتموها"
    },
    {
        "mot": "ضخمتموهم"
    },
    {
        "mot": "ضخمتموهن"
    },
    {
        "mot": "ضخمتنهما"
    },
    {
        "mot": "ضخمناكما"
    },
    {
        "mot": "ضخمناهما"
    },
    {
        "mot": "ضرائبكما"
    },
    {
        "mot": "ضرائبهما"
    },
    {
        "mot": "ضرائركما"
    },
    {
        "mot": "ضرائرهما"
    },
    {
        "mot": "ضراعتكما"
    },
    {
        "mot": "ضراعتهما"
    },
    {
        "mot": "ضراغمكما"
    },
    {
        "mot": "ضراغمهما"
    },
    {
        "mot": "ضراوتكما"
    },
    {
        "mot": "ضراوتهما"
    },
    {
        "mot": "ضرباتكما"
    },
    {
        "mot": "ضرباتهما"
    },
    {
        "mot": "ضربتاكما"
    },
    {
        "mot": "ضربتاهما"
    },
    {
        "mot": "ضربتمانا"
    },
    {
        "mot": "ضربتماني"
    },
    {
        "mot": "ضربتماها"
    },
    {
        "mot": "ضربتماهم"
    },
    {
        "mot": "ضربتماهن"
    },
    {
        "mot": "ضربتمونا"
    },
    {
        "mot": "ضربتموني"
    },
    {
        "mot": "ضربتموها"
    },
    {
        "mot": "ضربتموهم"
    },
    {
        "mot": "ضربتموهن"
    },
    {
        "mot": "ضربتنهما"
    },
    {
        "mot": "ضربتيكما"
    },
    {
        "mot": "ضربتيهما"
    },
    {
        "mot": "ضربناكما"
    },
    {
        "mot": "ضربناهما"
    },
    {
        "mot": "ضرتماهما"
    },
    {
        "mot": "ضرتموهما"
    },
    {
        "mot": "ضرستاكما"
    },
    {
        "mot": "ضرستاهما"
    },
    {
        "mot": "ضرستمانا"
    },
    {
        "mot": "ضرستماني"
    },
    {
        "mot": "ضرستماها"
    },
    {
        "mot": "ضرستماهم"
    },
    {
        "mot": "ضرستماهن"
    },
    {
        "mot": "ضرستمونا"
    },
    {
        "mot": "ضرستموني"
    },
    {
        "mot": "ضرستموها"
    },
    {
        "mot": "ضرستموهم"
    },
    {
        "mot": "ضرستموهن"
    },
    {
        "mot": "ضرستنهما"
    },
    {
        "mot": "ضرسناكما"
    },
    {
        "mot": "ضرسناهما"
    },
    {
        "mot": "ضرمتاكما"
    },
    {
        "mot": "ضرمتاهما"
    },
    {
        "mot": "ضرمتماها"
    },
    {
        "mot": "ضرمتماهم"
    },
    {
        "mot": "ضرمتماهن"
    },
    {
        "mot": "ضرمتنهما"
    },
    {
        "mot": "ضرمناهما"
    },
    {
        "mot": "ضروراتكم"
    },
    {
        "mot": "ضروراتكن"
    },
    {
        "mot": "ضروراتنا"
    },
    {
        "mot": "ضروراتها"
    },
    {
        "mot": "ضروراتهم"
    },
    {
        "mot": "ضروراتهن"
    },
    {
        "mot": "ضرورتكما"
    },
    {
        "mot": "ضرورتهما"
    },
    {
        "mot": "ضرورياته"
    },
    {
        "mot": "ضروريتان"
    },
    {
        "mot": "ضروريتها"
    },
    {
        "mot": "ضروريتين"
    },
    {
        "mot": "ضريبتاكم"
    },
    {
        "mot": "ضريبتاكن"
    },
    {
        "mot": "ضريبتانا"
    },
    {
        "mot": "ضريبتاها"
    },
    {
        "mot": "ضريبتاهم"
    },
    {
        "mot": "ضريبتاهن"
    },
    {
        "mot": "ضريبتكما"
    },
    {
        "mot": "ضريبتهما"
    },
    {
        "mot": "ضريبتيكم"
    },
    {
        "mot": "ضريبتيكن"
    },
    {
        "mot": "ضريبتينا"
    },
    {
        "mot": "ضريبتيها"
    },
    {
        "mot": "ضريبتيهم"
    },
    {
        "mot": "ضريبتيهن"
    },
    {
        "mot": "ضريبيتان"
    },
    {
        "mot": "ضريبيتين"
    },
    {
        "mot": "ضريحاكما"
    },
    {
        "mot": "ضريحاهما"
    },
    {
        "mot": "ضريحيكما"
    },
    {
        "mot": "ضريحيهما"
    },
    {
        "mot": "ضعتماهما"
    },
    {
        "mot": "ضعتموهما"
    },
    {
        "mot": "ضعضعاكما"
    },
    {
        "mot": "ضعضعاهما"
    },
    {
        "mot": "ضعضعتاكم"
    },
    {
        "mot": "ضعضعتاكن"
    },
    {
        "mot": "ضعضعتانا"
    },
    {
        "mot": "ضعضعتاني"
    },
    {
        "mot": "ضعضعتاها"
    },
    {
        "mot": "ضعضعتاهم"
    },
    {
        "mot": "ضعضعتاهن"
    },
    {
        "mot": "ضعضعتكما"
    },
    {
        "mot": "ضعضعتماه"
    },
    {
        "mot": "ضعضعتموه"
    },
    {
        "mot": "ضعضعتننا"
    },
    {
        "mot": "ضعضعتنني"
    },
    {
        "mot": "ضعضعتنها"
    },
    {
        "mot": "ضعضعتنهم"
    },
    {
        "mot": "ضعضعتنهن"
    },
    {
        "mot": "ضعضعتهما"
    },
    {
        "mot": "ضعضعناكم"
    },
    {
        "mot": "ضعضعناكن"
    },
    {
        "mot": "ضعضعناها"
    },
    {
        "mot": "ضعضعناهم"
    },
    {
        "mot": "ضعضعناهن"
    },
    {
        "mot": "ضعضعنكما"
    },
    {
        "mot": "ضعضعنهما"
    },
    {
        "mot": "ضعضعوكما"
    },
    {
        "mot": "ضعضعوهما"
    },
    {
        "mot": "ضعفتاكما"
    },
    {
        "mot": "ضعفتاهما"
    },
    {
        "mot": "ضعفتمانا"
    },
    {
        "mot": "ضعفتماني"
    },
    {
        "mot": "ضعفتماها"
    },
    {
        "mot": "ضعفتماهم"
    },
    {
        "mot": "ضعفتماهن"
    },
    {
        "mot": "ضعفتمونا"
    },
    {
        "mot": "ضعفتموني"
    },
    {
        "mot": "ضعفتموها"
    },
    {
        "mot": "ضعفتموهم"
    },
    {
        "mot": "ضعفتموهن"
    },
    {
        "mot": "ضعفتنهما"
    },
    {
        "mot": "ضعفناكما"
    },
    {
        "mot": "ضعفناهما"
    },
    {
        "mot": "ضغوطاتكم"
    },
    {
        "mot": "ضغوطاتكن"
    },
    {
        "mot": "ضغوطاتنا"
    },
    {
        "mot": "ضغوطاتها"
    },
    {
        "mot": "ضغوطاتهم"
    },
    {
        "mot": "ضغوطاتهن"
    },
    {
        "mot": "ضغينتكما"
    },
    {
        "mot": "ضغينتهما"
    },
    {
        "mot": "ضفائرهما"
    },
    {
        "mot": "ضفادعكما"
    },
    {
        "mot": "ضفادعهما"
    },
    {
        "mot": "ضفيرتكما"
    },
    {
        "mot": "ضفيرتهما"
    },
    {
        "mot": "ضفيرتيها"
    },
    {
        "mot": "ضلالاتنا"
    },
    {
        "mot": "ضلالاتها"
    },
    {
        "mot": "ضلالاتهم"
    },
    {
        "mot": "ضلعتاكما"
    },
    {
        "mot": "ضلعتاهما"
    },
    {
        "mot": "ضللتاكما"
    },
    {
        "mot": "ضللتاهما"
    },
    {
        "mot": "ضللتمانا"
    },
    {
        "mot": "ضللتماني"
    },
    {
        "mot": "ضللتماها"
    },
    {
        "mot": "ضللتماهم"
    },
    {
        "mot": "ضللتماهن"
    },
    {
        "mot": "ضللتمونا"
    },
    {
        "mot": "ضللتموني"
    },
    {
        "mot": "ضللتموها"
    },
    {
        "mot": "ضللتموهم"
    },
    {
        "mot": "ضللتموهن"
    },
    {
        "mot": "ضللتنهما"
    },
    {
        "mot": "ضللناكما"
    },
    {
        "mot": "ضللناهما"
    },
    {
        "mot": "ضمائدكما"
    },
    {
        "mot": "ضمائدهما"
    },
    {
        "mot": "ضمائركما"
    },
    {
        "mot": "ضمائرهما"
    },
    {
        "mot": "ضمائمكما"
    },
    {
        "mot": "ضمائمهما"
    },
    {
        "mot": "ضماداتكم"
    },
    {
        "mot": "ضماداتكن"
    },
    {
        "mot": "ضماداتنا"
    },
    {
        "mot": "ضماداتها"
    },
    {
        "mot": "ضماداتهم"
    },
    {
        "mot": "ضماداتهن"
    },
    {
        "mot": "ضمادتاكم"
    },
    {
        "mot": "ضمادتاكن"
    },
    {
        "mot": "ضمادتانا"
    },
    {
        "mot": "ضمادتاها"
    },
    {
        "mot": "ضمادتاهم"
    },
    {
        "mot": "ضمادتاهن"
    },
    {
        "mot": "ضمادتكما"
    },
    {
        "mot": "ضمادتهما"
    },
    {
        "mot": "ضمادتيكم"
    },
    {
        "mot": "ضمادتيكن"
    },
    {
        "mot": "ضمادتينا"
    },
    {
        "mot": "ضمادتيها"
    },
    {
        "mot": "ضمادتيهم"
    },
    {
        "mot": "ضمادتيهن"
    },
    {
        "mot": "ضماناتكم"
    },
    {
        "mot": "ضماناتكن"
    },
    {
        "mot": "ضماناتنا"
    },
    {
        "mot": "ضماناتها"
    },
    {
        "mot": "ضماناتهم"
    },
    {
        "mot": "ضماناتهن"
    },
    {
        "mot": "ضمانتكما"
    },
    {
        "mot": "ضمانتهما"
    },
    {
        "mot": "ضمدتاكما"
    },
    {
        "mot": "ضمدتاهما"
    },
    {
        "mot": "ضمدتمانا"
    },
    {
        "mot": "ضمدتماني"
    },
    {
        "mot": "ضمدتماها"
    },
    {
        "mot": "ضمدتماهم"
    },
    {
        "mot": "ضمدتماهن"
    },
    {
        "mot": "ضمدتمونا"
    },
    {
        "mot": "ضمدتموني"
    },
    {
        "mot": "ضمدتموها"
    },
    {
        "mot": "ضمدتموهم"
    },
    {
        "mot": "ضمدتموهن"
    },
    {
        "mot": "ضمدتنهما"
    },
    {
        "mot": "ضمدناكما"
    },
    {
        "mot": "ضمدناهما"
    },
    {
        "mot": "ضممتمانا"
    },
    {
        "mot": "ضممتماني"
    },
    {
        "mot": "ضممتماها"
    },
    {
        "mot": "ضممتماهم"
    },
    {
        "mot": "ضممتماهن"
    },
    {
        "mot": "ضممتمونا"
    },
    {
        "mot": "ضممتموني"
    },
    {
        "mot": "ضممتموها"
    },
    {
        "mot": "ضممتموهم"
    },
    {
        "mot": "ضممتموهن"
    },
    {
        "mot": "ضممتنهما"
    },
    {
        "mot": "ضممناكما"
    },
    {
        "mot": "ضممناهما"
    },
    {
        "mot": "ضمنتاكما"
    },
    {
        "mot": "ضمنتاهما"
    },
    {
        "mot": "ضمنتمانا"
    },
    {
        "mot": "ضمنتماني"
    },
    {
        "mot": "ضمنتماها"
    },
    {
        "mot": "ضمنتماهم"
    },
    {
        "mot": "ضمنتماهن"
    },
    {
        "mot": "ضمنتمونا"
    },
    {
        "mot": "ضمنتموني"
    },
    {
        "mot": "ضمنتموها"
    },
    {
        "mot": "ضمنتموهم"
    },
    {
        "mot": "ضمنتموهن"
    },
    {
        "mot": "ضمنتنهما"
    },
    {
        "mot": "ضميريتاك"
    },
    {
        "mot": "ضميريتان"
    },
    {
        "mot": "ضميريتاه"
    },
    {
        "mot": "ضميريتاي"
    },
    {
        "mot": "ضميريتكم"
    },
    {
        "mot": "ضميريتكن"
    },
    {
        "mot": "ضميريتنا"
    },
    {
        "mot": "ضميريتها"
    },
    {
        "mot": "ضميريتهم"
    },
    {
        "mot": "ضميريتهن"
    },
    {
        "mot": "ضميريتيك"
    },
    {
        "mot": "ضميريتين"
    },
    {
        "mot": "ضميريتيه"
    },
    {
        "mot": "ضميريكما"
    },
    {
        "mot": "ضميريهما"
    },
    {
        "mot": "ضميمتكما"
    },
    {
        "mot": "ضميمتهما"
    },
    {
        "mot": "ضوائقكما"
    },
    {
        "mot": "ضوائقهما"
    },
    {
        "mot": "ضوابطكما"
    },
    {
        "mot": "ضوابطهما"
    },
    {
        "mot": "ضواحيكما"
    },
    {
        "mot": "ضواحيهما"
    },
    {
        "mot": "ضواريكما"
    },
    {
        "mot": "ضواريهما"
    },
    {
        "mot": "ضوضاءكما"
    },
    {
        "mot": "ضوضاءهما"
    },
    {
        "mot": "ضوضاؤكما"
    },
    {
        "mot": "ضوضاؤهما"
    },
    {
        "mot": "ضوضائكما"
    },
    {
        "mot": "ضوضائهما"
    },
    {
        "mot": "ضوضائيين"
    },
    {
        "mot": "ضيائياكم"
    },
    {
        "mot": "ضيائياكن"
    },
    {
        "mot": "ضيائيانا"
    },
    {
        "mot": "ضيائياها"
    },
    {
        "mot": "ضيائياهم"
    },
    {
        "mot": "ضيائياهن"
    },
    {
        "mot": "ضيائيكما"
    },
    {
        "mot": "ضيائيهما"
    },
    {
        "mot": "ضيائييكم"
    },
    {
        "mot": "ضيائييكن"
    },
    {
        "mot": "ضيائيينا"
    },
    {
        "mot": "ضيائييها"
    },
    {
        "mot": "ضيائييهم"
    },
    {
        "mot": "ضيائييهن"
    },
    {
        "mot": "ضيافتكما"
    },
    {
        "mot": "ضيافتهما"
    },
    {
        "mot": "ضيعتاكما"
    },
    {
        "mot": "ضيعتاهما"
    },
    {
        "mot": "ضيعتمانا"
    },
    {
        "mot": "ضيعتماني"
    },
    {
        "mot": "ضيعتماها"
    },
    {
        "mot": "ضيعتماهم"
    },
    {
        "mot": "ضيعتماهن"
    },
    {
        "mot": "ضيعتمونا"
    },
    {
        "mot": "ضيعتموني"
    },
    {
        "mot": "ضيعتموها"
    },
    {
        "mot": "ضيعتموهم"
    },
    {
        "mot": "ضيعتموهن"
    },
    {
        "mot": "ضيعتنهما"
    },
    {
        "mot": "ضيعناكما"
    },
    {
        "mot": "ضيعناهما"
    },
    {
        "mot": "ضيفتاكما"
    },
    {
        "mot": "ضيفتاهما"
    },
    {
        "mot": "ضيفتمانا"
    },
    {
        "mot": "ضيفتماني"
    },
    {
        "mot": "ضيفتماها"
    },
    {
        "mot": "ضيفتماهم"
    },
    {
        "mot": "ضيفتماهن"
    },
    {
        "mot": "ضيفتمونا"
    },
    {
        "mot": "ضيفتموني"
    },
    {
        "mot": "ضيفتموها"
    },
    {
        "mot": "ضيفتموهم"
    },
    {
        "mot": "ضيفتموهن"
    },
    {
        "mot": "ضيفتنهما"
    },
    {
        "mot": "ضيفتيهما"
    },
    {
        "mot": "ضيفناكما"
    },
    {
        "mot": "ضيفناهما"
    },
    {
        "mot": "ظافراكما"
    },
    {
        "mot": "ظافراهما"
    },
    {
        "mot": "ظافريكما"
    },
    {
        "mot": "ظافريهما"
    },
    {
        "mot": "ظامئتاكم"
    },
    {
        "mot": "ظامئتاكن"
    },
    {
        "mot": "ظامئتانا"
    },
    {
        "mot": "ظامئتاها"
    },
    {
        "mot": "ظامئتاهم"
    },
    {
        "mot": "ظامئتاهن"
    },
    {
        "mot": "ظامئتكما"
    },
    {
        "mot": "ظامئتهما"
    },
    {
        "mot": "ظامئتيكم"
    },
    {
        "mot": "ظامئتيكن"
    },
    {
        "mot": "ظامئتينا"
    },
    {
        "mot": "ظامئتيها"
    },
    {
        "mot": "ظامئتيهم"
    },
    {
        "mot": "ظامئتيهن"
    },
    {
        "mot": "ظاهراتها"
    },
    {
        "mot": "ظاهراكما"
    },
    {
        "mot": "ظاهراهما"
    },
    {
        "mot": "ظاهرتاكم"
    },
    {
        "mot": "ظاهرتاكن"
    },
    {
        "mot": "ظاهرتانا"
    },
    {
        "mot": "ظاهرتاني"
    },
    {
        "mot": "ظاهرتاها"
    },
    {
        "mot": "ظاهرتاهم"
    },
    {
        "mot": "ظاهرتاهن"
    },
    {
        "mot": "ظاهرتكما"
    },
    {
        "mot": "ظاهرتماه"
    },
    {
        "mot": "ظاهرتموه"
    },
    {
        "mot": "ظاهرتننا"
    },
    {
        "mot": "ظاهرتنني"
    },
    {
        "mot": "ظاهرتنها"
    },
    {
        "mot": "ظاهرتنهم"
    },
    {
        "mot": "ظاهرتنهن"
    },
    {
        "mot": "ظاهرتهما"
    },
    {
        "mot": "ظاهرتيكم"
    },
    {
        "mot": "ظاهرتيكن"
    },
    {
        "mot": "ظاهرتينا"
    },
    {
        "mot": "ظاهرتيها"
    },
    {
        "mot": "ظاهرتيهم"
    },
    {
        "mot": "ظاهرتيهن"
    },
    {
        "mot": "ظاهرناكم"
    },
    {
        "mot": "ظاهرناكن"
    },
    {
        "mot": "ظاهرناها"
    },
    {
        "mot": "ظاهرناهم"
    },
    {
        "mot": "ظاهرناهن"
    },
    {
        "mot": "ظاهرنكما"
    },
    {
        "mot": "ظاهرنهما"
    },
    {
        "mot": "ظاهروكما"
    },
    {
        "mot": "ظاهروهما"
    },
    {
        "mot": "ظاهرياكم"
    },
    {
        "mot": "ظاهرياكن"
    },
    {
        "mot": "ظاهريانا"
    },
    {
        "mot": "ظاهرياها"
    },
    {
        "mot": "ظاهرياهم"
    },
    {
        "mot": "ظاهرياهن"
    },
    {
        "mot": "ظاهريتاك"
    },
    {
        "mot": "ظاهريتان"
    },
    {
        "mot": "ظاهريتاه"
    },
    {
        "mot": "ظاهريتاي"
    },
    {
        "mot": "ظاهريتكم"
    },
    {
        "mot": "ظاهريتكن"
    },
    {
        "mot": "ظاهريتنا"
    },
    {
        "mot": "ظاهريتها"
    },
    {
        "mot": "ظاهريتهم"
    },
    {
        "mot": "ظاهريتهن"
    },
    {
        "mot": "ظاهريتيك"
    },
    {
        "mot": "ظاهريتين"
    },
    {
        "mot": "ظاهريتيه"
    },
    {
        "mot": "ظاهريكما"
    },
    {
        "mot": "ظاهريهما"
    },
    {
        "mot": "ظاهرييكم"
    },
    {
        "mot": "ظاهرييكن"
    },
    {
        "mot": "ظاهريينا"
    },
    {
        "mot": "ظاهرييها"
    },
    {
        "mot": "ظاهرييهم"
    },
    {
        "mot": "ظاهرييهن"
    },
    {
        "mot": "ظرفياكما"
    },
    {
        "mot": "ظرفياهما"
    },
    {
        "mot": "ظرفيتاكم"
    },
    {
        "mot": "ظرفيتاكن"
    },
    {
        "mot": "ظرفيتانا"
    },
    {
        "mot": "ظرفيتاها"
    },
    {
        "mot": "ظرفيتاهم"
    },
    {
        "mot": "ظرفيتاهن"
    },
    {
        "mot": "ظرفيتكما"
    },
    {
        "mot": "ظرفيتهما"
    },
    {
        "mot": "ظرفيتيكم"
    },
    {
        "mot": "ظرفيتيكن"
    },
    {
        "mot": "ظرفيتينا"
    },
    {
        "mot": "ظرفيتيها"
    },
    {
        "mot": "ظرفيتيهم"
    },
    {
        "mot": "ظرفيتيهن"
    },
    {
        "mot": "ظرفييكما"
    },
    {
        "mot": "ظرفييهما"
    },
    {
        "mot": "ظريفاكما"
    },
    {
        "mot": "ظريفاهما"
    },
    {
        "mot": "ظريفتاكم"
    },
    {
        "mot": "ظريفتاكن"
    },
    {
        "mot": "ظريفتانا"
    },
    {
        "mot": "ظريفتاها"
    },
    {
        "mot": "ظريفتاهم"
    },
    {
        "mot": "ظريفتاهن"
    },
    {
        "mot": "ظريفتكما"
    },
    {
        "mot": "ظريفتهما"
    },
    {
        "mot": "ظريفتيكم"
    },
    {
        "mot": "ظريفتيكن"
    },
    {
        "mot": "ظريفتينا"
    },
    {
        "mot": "ظريفتيها"
    },
    {
        "mot": "ظريفتيهم"
    },
    {
        "mot": "ظريفتيهن"
    },
    {
        "mot": "ظريفيكما"
    },
    {
        "mot": "ظريفيهما"
    },
    {
        "mot": "ظعائنكما"
    },
    {
        "mot": "ظعائنهما"
    },
    {
        "mot": "ظلاماتكم"
    },
    {
        "mot": "ظلاماتكن"
    },
    {
        "mot": "ظلاماتنا"
    },
    {
        "mot": "ظلاماتها"
    },
    {
        "mot": "ظلاماتهم"
    },
    {
        "mot": "ظلاماتهن"
    },
    {
        "mot": "ظلامتاكم"
    },
    {
        "mot": "ظلامتاكن"
    },
    {
        "mot": "ظلامتانا"
    },
    {
        "mot": "ظلامتاها"
    },
    {
        "mot": "ظلامتاهم"
    },
    {
        "mot": "ظلامتاهن"
    },
    {
        "mot": "ظلامتكما"
    },
    {
        "mot": "ظلامتهما"
    },
    {
        "mot": "ظلامتيكم"
    },
    {
        "mot": "ظلامتيكن"
    },
    {
        "mot": "ظلامتينا"
    },
    {
        "mot": "ظلامتيها"
    },
    {
        "mot": "ظلامتيهم"
    },
    {
        "mot": "ظلامتيهن"
    },
    {
        "mot": "ظلامياكم"
    },
    {
        "mot": "ظلامياكن"
    },
    {
        "mot": "ظلاميانا"
    },
    {
        "mot": "ظلامياها"
    },
    {
        "mot": "ظلامياهم"
    },
    {
        "mot": "ظلامياهن"
    },
    {
        "mot": "ظلاميتاك"
    },
    {
        "mot": "ظلاميتان"
    },
    {
        "mot": "ظلاميتاه"
    },
    {
        "mot": "ظلاميتاي"
    },
    {
        "mot": "ظلاميتكم"
    },
    {
        "mot": "ظلاميتكن"
    },
    {
        "mot": "ظلاميتنا"
    },
    {
        "mot": "ظلاميتها"
    },
    {
        "mot": "ظلاميتهم"
    },
    {
        "mot": "ظلاميتهن"
    },
    {
        "mot": "ظلاميتيك"
    },
    {
        "mot": "ظلاميتين"
    },
    {
        "mot": "ظلاميتيه"
    },
    {
        "mot": "ظلاميكما"
    },
    {
        "mot": "ظلاميهما"
    },
    {
        "mot": "ظلاميوكم"
    },
    {
        "mot": "ظلاميوكن"
    },
    {
        "mot": "ظلاميونا"
    },
    {
        "mot": "ظلاميوها"
    },
    {
        "mot": "ظلاميوهم"
    },
    {
        "mot": "ظلاميوهن"
    },
    {
        "mot": "ظلامييكم"
    },
    {
        "mot": "ظلامييكن"
    },
    {
        "mot": "ظلاميينا"
    },
    {
        "mot": "ظلامييها"
    },
    {
        "mot": "ظلامييهم"
    },
    {
        "mot": "ظلامييهن"
    },
    {
        "mot": "ظللتاكما"
    },
    {
        "mot": "ظللتاهما"
    },
    {
        "mot": "ظللتمانا"
    },
    {
        "mot": "ظللتماني"
    },
    {
        "mot": "ظللتماها"
    },
    {
        "mot": "ظللتماهم"
    },
    {
        "mot": "ظللتماهن"
    },
    {
        "mot": "ظللتمونا"
    },
    {
        "mot": "ظللتموني"
    },
    {
        "mot": "ظللتموها"
    },
    {
        "mot": "ظللتموهم"
    },
    {
        "mot": "ظللتموهن"
    },
    {
        "mot": "ظللتنهما"
    },
    {
        "mot": "ظللناكما"
    },
    {
        "mot": "ظللناهما"
    },
    {
        "mot": "ظلماتكما"
    },
    {
        "mot": "ظلماتهما"
    },
    {
        "mot": "ظلمتاكما"
    },
    {
        "mot": "ظلمتاهما"
    },
    {
        "mot": "ظلمتمانا"
    },
    {
        "mot": "ظلمتماني"
    },
    {
        "mot": "ظلمتماها"
    },
    {
        "mot": "ظلمتماهم"
    },
    {
        "mot": "ظلمتماهن"
    },
    {
        "mot": "ظلمتمونا"
    },
    {
        "mot": "ظلمتموني"
    },
    {
        "mot": "ظلمتموها"
    },
    {
        "mot": "ظلمتموهم"
    },
    {
        "mot": "ظلمتموهن"
    },
    {
        "mot": "ظلمتنهما"
    },
    {
        "mot": "ظلمتيكما"
    },
    {
        "mot": "ظلمتيهما"
    },
    {
        "mot": "ظلمناكما"
    },
    {
        "mot": "ظلمناهما"
    },
    {
        "mot": "ظليلتاكم"
    },
    {
        "mot": "ظليلتاكن"
    },
    {
        "mot": "ظليلتانا"
    },
    {
        "mot": "ظليلتاها"
    },
    {
        "mot": "ظليلتاهم"
    },
    {
        "mot": "ظليلتاهن"
    },
    {
        "mot": "ظليلتيكم"
    },
    {
        "mot": "ظليلتيكن"
    },
    {
        "mot": "ظليلتينا"
    },
    {
        "mot": "ظليلتيها"
    },
    {
        "mot": "ظليلتيهم"
    },
    {
        "mot": "ظليلتيهن"
    },
    {
        "mot": "ظليماكما"
    },
    {
        "mot": "ظليماهما"
    },
    {
        "mot": "ظليميكما"
    },
    {
        "mot": "ظليميهما"
    },
    {
        "mot": "ظمأتاكما"
    },
    {
        "mot": "ظمأتاهما"
    },
    {
        "mot": "ظمأتمانا"
    },
    {
        "mot": "ظمأتماني"
    },
    {
        "mot": "ظمأتماها"
    },
    {
        "mot": "ظمأتماهم"
    },
    {
        "mot": "ظمأتماهن"
    },
    {
        "mot": "ظمأتمونا"
    },
    {
        "mot": "ظمأتموني"
    },
    {
        "mot": "ظمأتموها"
    },
    {
        "mot": "ظمأتموهم"
    },
    {
        "mot": "ظمأتموهن"
    },
    {
        "mot": "ظمأتنهما"
    },
    {
        "mot": "ظمأناكما"
    },
    {
        "mot": "ظمأناهما"
    },
    {
        "mot": "ظننتمانا"
    },
    {
        "mot": "ظننتماني"
    },
    {
        "mot": "ظننتماها"
    },
    {
        "mot": "ظننتماهم"
    },
    {
        "mot": "ظننتماهن"
    },
    {
        "mot": "ظننتمونا"
    },
    {
        "mot": "ظننتموني"
    },
    {
        "mot": "ظننتموها"
    },
    {
        "mot": "ظننتموهم"
    },
    {
        "mot": "ظننتموهن"
    },
    {
        "mot": "ظننتنهما"
    },
    {
        "mot": "ظنياتكما"
    },
    {
        "mot": "ظنياتهما"
    },
    {
        "mot": "ظنيتاكما"
    },
    {
        "mot": "ظنيتاهما"
    },
    {
        "mot": "ظنيتيكما"
    },
    {
        "mot": "ظنيتيهما"
    },
    {
        "mot": "ظهارتكما"
    },
    {
        "mot": "ظهارتهما"
    },
    {
        "mot": "ظهيراكما"
    },
    {
        "mot": "ظهيراهما"
    },
    {
        "mot": "ظهيرتاكم"
    },
    {
        "mot": "ظهيرتاكن"
    },
    {
        "mot": "ظهيرتانا"
    },
    {
        "mot": "ظهيرتاها"
    },
    {
        "mot": "ظهيرتاهم"
    },
    {
        "mot": "ظهيرتاهن"
    },
    {
        "mot": "ظهيرتكما"
    },
    {
        "mot": "ظهيرتهما"
    },
    {
        "mot": "ظهيرتيكم"
    },
    {
        "mot": "ظهيرتيكن"
    },
    {
        "mot": "ظهيرتينا"
    },
    {
        "mot": "ظهيرتيها"
    },
    {
        "mot": "ظهيرتيهم"
    },
    {
        "mot": "ظهيرتيهن"
    },
    {
        "mot": "ظهيريكما"
    },
    {
        "mot": "ظهيريهما"
    },
    {
        "mot": "ظواهركما"
    },
    {
        "mot": "ظواهرهما"
    },
    {
        "mot": "ضرورياتك"
    },
    {
        "mot": "ضرورياتي"
    },
    {
        "mot": "ضفيرتاها"
    },
    {
        "mot": "ظهرانيها"
    },
    {
        "mot": "ظهرانينا"
    },
    {
        "mot": "ظهرانيهم"
    }
]
