[
    {
        "mot": "جأر"
    },
    {
        "mot": "جأش"
    },
    {
        "mot": "جئت"
    },
    {
        "mot": "جئر"
    },
    {
        "mot": "جئش"
    },
    {
        "mot": "جئن"
    },
    {
        "mot": "جاء"
    },
    {
        "mot": "جاب"
    },
    {
        "mot": "جاث"
    },
    {
        "mot": "جاح"
    },
    {
        "mot": "جاخ"
    },
    {
        "mot": "جاد"
    },
    {
        "mot": "جاذ"
    },
    {
        "mot": "جار"
    },
    {
        "mot": "جاز"
    },
    {
        "mot": "جاس"
    },
    {
        "mot": "جاش"
    },
    {
        "mot": "جاع"
    },
    {
        "mot": "جاف"
    },
    {
        "mot": "جاك"
    },
    {
        "mot": "جال"
    },
    {
        "mot": "جام"
    },
    {
        "mot": "جان"
    },
    {
        "mot": "جاه"
    },
    {
        "mot": "جاو"
    },
    {
        "mot": "جبا"
    },
    {
        "mot": "جبب"
    },
    {
        "mot": "جبة"
    },
    {
        "mot": "جبذ"
    },
    {
        "mot": "جبر"
    },
    {
        "mot": "جبس"
    },
    {
        "mot": "جبك"
    },
    {
        "mot": "جبل"
    },
    {
        "mot": "جبن"
    },
    {
        "mot": "جبى"
    },
    {
        "mot": "جبي"
    },
    {
        "mot": "جثا"
    },
    {
        "mot": "جثة"
    },
    {
        "mot": "جثت"
    },
    {
        "mot": "جثث"
    },
    {
        "mot": "جثك"
    },
    {
        "mot": "جثل"
    },
    {
        "mot": "جثم"
    },
    {
        "mot": "جثه"
    },
    {
        "mot": "جثو"
    },
    {
        "mot": "جثى"
    },
    {
        "mot": "جثي"
    },
    {
        "mot": "جحا"
    },
    {
        "mot": "جحت"
    },
    {
        "mot": "جحد"
    },
    {
        "mot": "جحر"
    },
    {
        "mot": "جحش"
    },
    {
        "mot": "جحظ"
    },
    {
        "mot": "جحف"
    },
    {
        "mot": "جحك"
    },
    {
        "mot": "جحل"
    },
    {
        "mot": "جحم"
    },
    {
        "mot": "جحن"
    },
    {
        "mot": "جحي"
    },
    {
        "mot": "جدا"
    },
    {
        "mot": "جدب"
    },
    {
        "mot": "جدة"
    },
    {
        "mot": "جدت"
    },
    {
        "mot": "جدث"
    },
    {
        "mot": "جدح"
    },
    {
        "mot": "جدد"
    },
    {
        "mot": "جدر"
    },
    {
        "mot": "جدع"
    },
    {
        "mot": "جدف"
    },
    {
        "mot": "جدك"
    },
    {
        "mot": "جدل"
    },
    {
        "mot": "جدم"
    },
    {
        "mot": "جده"
    },
    {
        "mot": "جدو"
    },
    {
        "mot": "جدي"
    },
    {
        "mot": "جذا"
    },
    {
        "mot": "جذب"
    },
    {
        "mot": "جذت"
    },
    {
        "mot": "جذر"
    },
    {
        "mot": "جذع"
    },
    {
        "mot": "جذف"
    },
    {
        "mot": "جذل"
    },
    {
        "mot": "جذم"
    },
    {
        "mot": "جذو"
    },
    {
        "mot": "جذى"
    },
    {
        "mot": "جذي"
    },
    {
        "mot": "جرآ"
    },
    {
        "mot": "جرأ"
    },
    {
        "mot": "جرؤ"
    },
    {
        "mot": "جرئ"
    },
    {
        "mot": "جرا"
    },
    {
        "mot": "جرب"
    },
    {
        "mot": "جرة"
    },
    {
        "mot": "جرت"
    },
    {
        "mot": "جرج"
    },
    {
        "mot": "جرح"
    },
    {
        "mot": "جرد"
    },
    {
        "mot": "جرذ"
    },
    {
        "mot": "جرر"
    },
    {
        "mot": "جرس"
    },
    {
        "mot": "جرش"
    },
    {
        "mot": "جرض"
    },
    {
        "mot": "جرع"
    },
    {
        "mot": "جرف"
    },
    {
        "mot": "جرك"
    },
    {
        "mot": "جرل"
    },
    {
        "mot": "جرم"
    },
    {
        "mot": "جرن"
    },
    {
        "mot": "جره"
    },
    {
        "mot": "جرو"
    },
    {
        "mot": "جرى"
    },
    {
        "mot": "جري"
    },
    {
        "mot": "جزء"
    },
    {
        "mot": "جزآ"
    },
    {
        "mot": "جزأ"
    },
    {
        "mot": "جزب"
    },
    {
        "mot": "جزة"
    },
    {
        "mot": "جزت"
    },
    {
        "mot": "جزر"
    },
    {
        "mot": "جزز"
    },
    {
        "mot": "جزع"
    },
    {
        "mot": "جزف"
    },
    {
        "mot": "جزك"
    },
    {
        "mot": "جزل"
    },
    {
        "mot": "جزم"
    },
    {
        "mot": "جزن"
    },
    {
        "mot": "جزه"
    },
    {
        "mot": "جزى"
    },
    {
        "mot": "جزي"
    },
    {
        "mot": "جسا"
    },
    {
        "mot": "جست"
    },
    {
        "mot": "جسد"
    },
    {
        "mot": "جسر"
    },
    {
        "mot": "جسس"
    },
    {
        "mot": "جسك"
    },
    {
        "mot": "جسم"
    },
    {
        "mot": "جسن"
    },
    {
        "mot": "جسه"
    },
    {
        "mot": "جسو"
    },
    {
        "mot": "جسي"
    },
    {
        "mot": "جشء"
    },
    {
        "mot": "جشآ"
    },
    {
        "mot": "جشأ"
    },
    {
        "mot": "جشئ"
    },
    {
        "mot": "جشا"
    },
    {
        "mot": "جشة"
    },
    {
        "mot": "جشت"
    },
    {
        "mot": "جشر"
    },
    {
        "mot": "جشش"
    },
    {
        "mot": "جشع"
    },
    {
        "mot": "جشك"
    },
    {
        "mot": "جشم"
    },
    {
        "mot": "جشن"
    },
    {
        "mot": "جشه"
    },
    {
        "mot": "جشي"
    },
    {
        "mot": "جصا"
    },
    {
        "mot": "جصص"
    },
    {
        "mot": "جصك"
    },
    {
        "mot": "جصه"
    },
    {
        "mot": "جصي"
    },
    {
        "mot": "جضم"
    },
    {
        "mot": "جطو"
    },
    {
        "mot": "جظي"
    },
    {
        "mot": "جعا"
    },
    {
        "mot": "جعب"
    },
    {
        "mot": "جعة"
    },
    {
        "mot": "جعت"
    },
    {
        "mot": "جعد"
    },
    {
        "mot": "جعر"
    },
    {
        "mot": "جعل"
    },
    {
        "mot": "جعن"
    },
    {
        "mot": "جعي"
    },
    {
        "mot": "جفا"
    },
    {
        "mot": "جفت"
    },
    {
        "mot": "جفر"
    },
    {
        "mot": "جفف"
    },
    {
        "mot": "جفك"
    },
    {
        "mot": "جفل"
    },
    {
        "mot": "جفن"
    },
    {
        "mot": "جفى"
    },
    {
        "mot": "جفي"
    },
    {
        "mot": "جقه"
    },
    {
        "mot": "جكس"
    },
    {
        "mot": "جلب"
    },
    {
        "mot": "جلت"
    },
    {
        "mot": "جلح"
    },
    {
        "mot": "جلخ"
    },
    {
        "mot": "جلد"
    },
    {
        "mot": "جلس"
    },
    {
        "mot": "جلط"
    },
    {
        "mot": "جلف"
    },
    {
        "mot": "جلك"
    },
    {
        "mot": "جلل"
    },
    {
        "mot": "جلم"
    },
    {
        "mot": "جلن"
    },
    {
        "mot": "جلو"
    },
    {
        "mot": "جلي"
    },
    {
        "mot": "جما"
    },
    {
        "mot": "جمة"
    },
    {
        "mot": "جمت"
    },
    {
        "mot": "جمح"
    },
    {
        "mot": "جمد"
    },
    {
        "mot": "جمر"
    },
    {
        "mot": "جمز"
    },
    {
        "mot": "جمس"
    },
    {
        "mot": "جمع"
    },
    {
        "mot": "جمك"
    },
    {
        "mot": "جمل"
    },
    {
        "mot": "جمم"
    },
    {
        "mot": "جمن"
    },
    {
        "mot": "جمه"
    },
    {
        "mot": "جمو"
    },
    {
        "mot": "جمي"
    },
    {
        "mot": "جنا"
    },
    {
        "mot": "جنب"
    },
    {
        "mot": "جنة"
    },
    {
        "mot": "جنت"
    },
    {
        "mot": "جنث"
    },
    {
        "mot": "جنح"
    },
    {
        "mot": "جند"
    },
    {
        "mot": "جنس"
    },
    {
        "mot": "جنش"
    },
    {
        "mot": "جنف"
    },
    {
        "mot": "جنق"
    },
    {
        "mot": "جنك"
    },
    {
        "mot": "جنن"
    },
    {
        "mot": "جنى"
    },
    {
        "mot": "جني"
    },
    {
        "mot": "جها"
    },
    {
        "mot": "جهة"
    },
    {
        "mot": "جهد"
    },
    {
        "mot": "جهر"
    },
    {
        "mot": "جهز"
    },
    {
        "mot": "جهش"
    },
    {
        "mot": "جهض"
    },
    {
        "mot": "جهل"
    },
    {
        "mot": "جهم"
    },
    {
        "mot": "جهن"
    },
    {
        "mot": "جهى"
    },
    {
        "mot": "جهي"
    },
    {
        "mot": "جوا"
    },
    {
        "mot": "جوب"
    },
    {
        "mot": "جوة"
    },
    {
        "mot": "جوت"
    },
    {
        "mot": "جوث"
    },
    {
        "mot": "جوح"
    },
    {
        "mot": "جوخ"
    },
    {
        "mot": "جود"
    },
    {
        "mot": "جور"
    },
    {
        "mot": "جوز"
    },
    {
        "mot": "جوس"
    },
    {
        "mot": "جوع"
    },
    {
        "mot": "جوف"
    },
    {
        "mot": "جوق"
    },
    {
        "mot": "جوك"
    },
    {
        "mot": "جول"
    },
    {
        "mot": "جوم"
    },
    {
        "mot": "جون"
    },
    {
        "mot": "جوي"
    },
    {
        "mot": "جيء"
    },
    {
        "mot": "جيا"
    },
    {
        "mot": "جيب"
    },
    {
        "mot": "جية"
    },
    {
        "mot": "جيت"
    },
    {
        "mot": "جيح"
    },
    {
        "mot": "جيد"
    },
    {
        "mot": "جير"
    },
    {
        "mot": "جيز"
    },
    {
        "mot": "جيش"
    },
    {
        "mot": "جيع"
    },
    {
        "mot": "جيف"
    },
    {
        "mot": "جيق"
    },
    {
        "mot": "جيك"
    },
    {
        "mot": "جيل"
    },
    {
        "mot": "جيم"
    },
    {
        "mot": "جين"
    },
    {
        "mot": "جيه"
    },
    {
        "mot": "جيي"
    },
    {
        "mot": "جاق"
    },
    {
        "mot": "جحه"
    },
    {
        "mot": "جبع"
    }
]
